CHANGES.txt
README.txt
setup.py
cc/__init__.py
cc.gettext.egg-info/PKG-INFO
cc.gettext.egg-info/SOURCES.txt
cc.gettext.egg-info/dependency_links.txt
cc.gettext.egg-info/entry_points.txt
cc.gettext.egg-info/namespace_packages.txt
cc.gettext.egg-info/requires.txt
cc.gettext.egg-info/top_level.txt
cc/gettext/__init__.py
