Metadata-Version: 1.0
Name: cc.gettext
Version: 0.6
Summary: Recipe for manipulating gettext message catalogs.
Home-page: http://python.org/pypi/cc.gettext/
Author: Nathan R. Yergler
Author-email: nathan@creativecommons.org
License: ZPL 2.1
Keywords: development build gettext
Platform: UNKNOWN
Classifier: Framework :: Buildout
Classifier: Development Status :: 4 - Beta
Classifier: Intended Audience :: Developers
Classifier: License :: OSI Approved :: Zope Public License
Classifier: Topic :: Software Development :: Build Tools
Classifier: Topic :: Software Development :: Libraries :: Python Modules
